wdp/__init__.py
wdp/const.py
wdp/format.py
wdp/models.py
wdp/upload.py
wdp/validate.py
wdp-0.0.6.dist-info/AUTHORS.rst
wdp-0.0.6.dist-info/LICENSE.txt
wdp-0.0.6.dist-info/METADATA
wdp-0.0.6.dist-info/WHEEL
wdp-0.0.6.dist-info/top_level.txt
wdp-0.0.6.dist-info/RECORD
