Metadata-Version: 2.1
Name: wdp
Version: 0.0.6
Summary: Wiktionary Data Preparer
Home-page: https://github.com/lgessler/wdp
Author: Luke Gessler
Author-email: lukegessler@gmail.com
License: mit
Project-URL: Documentation, https://github.com/lgessler/wdp
Platform: any
Classifier: Development Status :: 4 - Beta
Classifier: Programming Language :: Python
Classifier: Programming Language :: Python :: 3
Requires-Python: >=3.6
Requires-Dist: jinja2
Requires-Dist: pywikibot
Provides-Extra: testing
Requires-Dist: pytest ; extra == 'testing'
Requires-Dist: pytest-cov ; extra == 'testing'
Requires-Dist: sphinx-rtd-theme ; extra == 'testing'
